LICENSE
README.md
setup.py
deepneuron/__init__.py
deepneuron/deepnet.py
deepneuron.egg-info/PKG-INFO
deepneuron.egg-info/SOURCES.txt
deepneuron.egg-info/dependency_links.txt
deepneuron.egg-info/requires.txt
deepneuron.egg-info/top_level.txt