Metadata-Version: 2.1
Name: deepneuron
Version: 0.0.3
Summary: Create neural networks
Author: Vignesh Reddy
Author-email: <vignesh77reddy@gmail.com>
Keywords: python,neural,network,neural network,deep learning,deep,learning
Classifier: Development Status :: 5 - Production/Stable
Classifier: Intended Audience :: Developers
Classifier: Programming Language :: Python :: 3
Classifier: Operating System :: Unix
Classifier: Operating System :: MacOS :: MacOS X
Classifier: Operating System :: Microsoft :: Windows
Classifier: License :: OSI Approved :: MIT License
License-File: LICENSE
